{"driver":"STM32F4xx","URL":"https://github.com/grblHAL/STM32F4xx","board":"BOARD_LONGBOARD32_EXT","my_plugin":["https://github.com/grblHAL/Templates/tree/master/my_plugin/Persistent_tool"],"symbols":["USE_HAL_DRIVER","ETH_TX_DESC_CNT=12","TCP_MSS=1460","TCP_SND_BUF=5840","LWIP_NUM_NETIF_CLIENT_DATA=2","LWIP_HTTPD_CUSTOM_FILES=0","MEM_SIZE=16384","LWIP_IGMP=1","LWIP_MDNS_RESPONDER=1","LWIP_NETIF_STATUS_CALLBACK=1","LWIP_HTTPD_DYNAMIC_HEADERS=1","LWIP_HTTPD_DYNAMIC_FILE_READ=1","LWIP_HTTPD_SUPPORT_V09=0","LWIP_HTTPD_SUPPORT_11_KEEPALIVE=1","LWIP_HTTPD_CGI_ADV=1","LWIP_HTTPD_SUPPORT_POST=1","LWIP_HTTPD_SUPPORT_WEBDAV=1","STM32F412Vx","STEP_PULSE_LATENCY=1.3","RTC_ENABLE=1","USB_SERIAL_CDC=1","N_AXIS=4","Y_AUTO_SQUARE=1","PROBE_ENABLE=1","MODBUS_ENABLE=1","MODBUS_BAUDRATE=3","EEPROM_ENABLE=128","SDCARD_ENABLE=1","KEYPAD_ENABLE=1","MACROS_ENABLE=3","N_MACROS=3","RGB_LED_ENABLE=2","EVENTOUT_ENABLE=1","N_EVENTS=4","FEED_OVERRIDE_ENABLE=1","WEBUI_ENABLE=3","_WIZCHIP_=5500","ETHERNET_ENABLE=1","TELNET_ENABLE=1","WEBSOCKET_ENABLE=1","FTP_ENABLE=1","HTTP_ENABLE=1","MDNS_ENABLE=1","ESTOP_ENABLE=1","DEFAULT_SLEEP_ENABLE=1","MINIMIZE_PROBE_OVERSHOOT=1","NGC_EXPRESSIONS_ENABLE=1","STATUS_LIGHT_ENABLE=2","ADD_MY_PLUGIN=1","SPINDLE0_ENABLE=6","SPINDLE1_ENABLE=1","N_SPINDLE=2"],"docker_instance":"","grblHAL":"webBuilder"}